Workbook

Sheet Read me
B2: Afe — unit economics and viability model
B3: Companion to Afe Project Statement v3.3, Section 12 (Business model and viability)
B5: EVERY NUMBER IN THIS MODEL IS A PLACEHOLDER.
B6: The figures carried over from the project documents are the 3.5% platform fee (architecture.md, page-structure.md)
B7: and the USD 50/month premium agent subscription (page-structure.md). Everything else — rents, volumes, costs,
B8: growth rates — is illustrative and must be replaced with the numbers from the viability and monetization analysis.
B10: How to use it
B11: 1. Open the Inputs sheet. Every cell with a yellow fill and blue text is yours to change. Nothing else should be edited.
B12: 2. Unit economics shows what one escrow transaction and one subscribed agent are worth after costs.
B13: 3. Projection runs 24 months from kick-off and shows the month the business turns cash-positive.
B14: 4. Black text is a formula. Green text is a link to another sheet. Do not type over either.
B16: Questions this model is meant to answer
... B26: D23 Funding position and runway.

Sheet Inputs
B2: Inputs
B3: Yellow cells with blue text are yours to edit. Replace every one with a figure from the viability analysis.
B5: Pricing | C5: Value | D5: Note / source
B6: Platform fee on escrowed amount | C6: 0.035 | D6: From architecture.md and page-structure.md. RFC-002 says 2.5% — one rate must win (D6).
B7: Premium agent subscription (GHS / month) | C7: 600 | D7: page-structure.md says USD 50/month. Check against what Ghana agents will pay (D22).
B8: Featured listing fee (GHS, each) | C8: 150 | D8: Release 2 revenue stream. Illustrative.
B10: Transaction size | C10: Value | D10: Note / source
B11: Average monthly rent (GHS) | C11: 2000 | D11: ILLUSTRATIVE — replace with real Accra/Kumasi data.
B12: Months of advance rent escrowed | C12: 6 | D12: Act 220 cap for tenancies over six months.
B13: Deposit months escrowed | C13: 1 | D13: ILLUSTRATIVE.
B14: Average escrowed amount (GHS) | C14: =$C$11*($C$12+$C$13) -> 14000 | D14: Calculated — do not edit.
B16: Cost per transaction | C16: Value | D16: Note / source
B17: Payment gateway fee (% of amount) | C17: 0.018 | D17: Confirm with Hubtel / Paystack (D4). architecture.md says 1.5–2.0%.
B18: Identity checks (GHS per transaction) | C18: 8 | D18: Ghana Card + agent licence lookups. ILLUSTRATIVE.
B19: SMS and notifications (GHS per transaction) | C19: 3 | D19: ILLUSTRATIVE.
B20: Review, support and disputes (GHS per transaction) | C20: 25 | D20: Reviewer time on the listing and any dispute. ILLUSTRATIVE.
B21: Storage and image delivery (GHS per transaction) | C21: 2 | D21: S3 + CloudFront share. ILLUSTRATIVE.
B23: Cost per subscribed agent | C23: Value | D23: Note / source
B24: Support and servicing (GHS / month) | C24: 40 | D24: ILLUSTRATIVE.
B26: Volumes and growth | C26: Value | D26: Note / source
B27: First month with live revenue | C27: 7 | D27: Statement Section 11: Ghana launch around week 28.
B28: Escrow transactions in the first revenue month | C28: 15 | D28: ILLUSTRATIVE.
B29: Monthly growth in transactions | C29: 0.2 | D29: ILLUSTRATIVE.
B30: Share of deals that actually use escrow | C30: 0.6 | D30: The rest leak off-platform. The single most important number here.
B31: Subscribed agents in the first revenue month | C31: 10 | D31: ILLUSTRATIVE.
B32: Monthly growth in subscribed agents | C32: 0.15 | D32: ILLUSTRATIVE.
B33: Featured listings sold per month (from month 13) | C33: 0 | D33: Release 2. Leave at 0 until it ships.
B35: Fixed monthly costs | C35: Value | D35: Note / source
B36: Team (GHS / month, all salaries) | C36: 60000 | D36: Statement Section 13 team. ILLUSTRATIVE — re-cost against Ghana rates.
B37: Infrastructure (GHS / month) | C37: 6000 | D37: AWS, from the cost tables in architecture.md. ILLUSTRATIVE.
B38: Legal and compliance (GHS / month) | C38: 5000 | D38: Counsel retainer, DPC registration. ILLUSTRATIVE.
B39: Marketing and agent acquisition (GHS / month) | C39: 10000 | D39: ILLUSTRATIVE.
B40: Other overheads (GHS / month) | C40: 4000 | D40: Office, tools, accounting. ILLUSTRATIVE.
B41: Total fixed costs (GHS / month) | C41: =SUM(C36:C40) -> 85000
B43: Funding | C43: Value | D43: Note / source
B44: Cash available at kick-off (GHS) | C44: 400000 | D44: ILLUSTRATIVE — replace with the real position (D23).
B45: GHS per USD | C45: 12 | D45: For reporting only. Update to the current rate.

Sheet Unit economics
B2: Unit economics
B3: What one completed rental and one subscribed agent are worth after direct costs.
B5: One escrow transaction | C5: Value | D5: Note / source
B6: Escrowed amount | C6: =Inputs!$C$14 -> 14000 | D6: Advance rent plus deposit
B7: Platform fee revenue | C7: =C6*Inputs!$C$6 -> 490 | D7: Deducted when escrow is released
B8: Payment gateway cost | C8: =-C6*Inputs!$C$17 -> -252 | D8: Charged on the full amount moved
B9: Identity checks | C9: =-Inputs!$C$18 -> -8
B10: SMS and notifications | C10: =-Inputs!$C$19 -> -3
B11: Review, support and disputes | C11: =-Inputs!$C$20 -> -25
B12: Storage and image delivery | C12: =-Inputs!$C$21 -> -2
B13: Contribution per transaction | C13: =SUM(C7:C12) -> 200 | D13: Negative means every completed rental loses money
B14: Contribution margin on fee revenue | C14: =IFERROR(C13/C7,0) -> 0.40816327 | D14: Below zero: the gateway and checks cost more than the fee
B16: One subscribed agent | C16: Value | D16: Note / source
B17: Subscription revenue (per month) | C17: =Inputs!$C$7 -> 600
B18: Support and servicing | C18: =-Inputs!$C$24 -> -40
B19: Contribution per agent per month | C19: =SUM(C17:C18) -> 560
B21: Sanity checks | C21: Value | D21: Note / source
B22: Fee as a share of one month's rent | C22: =IFERROR(C7/Inputs!$C$11,0) -> 0.245 | D22: If this is near or above one month's rent, expect heavy leakage
B23: Transactions needed to cover fixed costs (no subscriptions) | C23: =IFERROR(IF(C13<=0,"never",Inputs!$C$41/C13),0) -> 425 | D23: Compare with the Projection sheet
B24: Contribution per transaction (USD) | C24: =IFERROR(C13/Inputs!$C$45,0) -> 16.666667 | D24: For investor conversations

Sheet Projection
B2: 24-month projection
B3: Month 1 is kick-off. Revenue starts in the launch month set on the Inputs sheet.
B5: Month | C5: M1 | D5: M2 | E5: M3 | F5: M4 | G5: M5 | H5: M6 | I5: M7 | J5: M8 | K5: M9 | L5: M10 | M5: M11 | N5: M12 | O5: M13 | P5: M14 | Q5: M15 | R5: M16 | S5: M17 | T5: M18 | U5: M19 | V5: M20 | W5: M21 | X5: M22 | Y5: M23 | Z5: M24
B6: Months since launch | C6: =MAX(0,1-Inputs!$C$27+1) -> 0 | D6: =MAX(0,2-Inputs!$C$27+1) -> 0 | E6: =MAX(0,3-Inputs!$C$27+1) -> 0 | F6: =MAX(0,4-Inputs!$C$27+1) -> 0 | G6: =MAX(0,5-Inputs!$C$27+1) -> 0 | H6: =MAX(0,6-Inputs!$C$27+1) -> 0 | I6: =MAX(0,7-Inputs!$C$27+1) -> 1 | J6: =MAX(0,8-Inputs!$C$27+1) -> 2 | K6: =MAX(0,9-Inputs!$C$27+1) -> 3 | L6: =MAX(0,10-Inputs!$C$27+1) -> 4 | M6: =MAX(0,11-Inputs!$C$27+1) -> 5 | N6: =MAX(0,12-Inputs!$C$27+1) -> 6 | O6: =MAX(0,13-Inputs!$C$27+1) -> 7 | P6: =MAX(0,14-Inputs!$C$27+1) -> 8 | Q6: =MAX(0,15-Inputs!$C$27+1) -> 9 | R6: =MAX(0,16-Inputs!$C$27+1) -> 10 | S6: =MAX(0,17-Inputs!$C$27+1) -> 11 | T6: =MAX(0,18-Inputs!$C$27+1) -> 12 | U6: =MAX(0,19-Inputs!$C$27+1) -> 13 | V6: =MAX(0,20-Inputs!$C$27+1) -> 14 | W6: =MAX(0,21-Inputs!$C$27+1) -> 15 | X6: =MAX(0,22-Inputs!$C$27+1) -> 16 | Y6: =MAX(0,23-Inputs!$C$27+1) -> 17 | Z6: =MAX(0,24-Inputs!$C$27+1) -> 18
B7: Escrow transactions | C7: =IF(C$6=0,0,Inputs!$C$28*(1+Inputs!$C$29)^(C$6-1)*Inputs!$C$30) -> 0 | D7: =IF(D$6=0,0,Inputs!$C$28*(1+Inputs!$C$29)^(D$6-1)*Inputs!$C$30) -> 0 | E7: =IF(E$6=0,0,Inputs!$C$28*(1+Inputs!$C$29)^(E$6-1)*Inputs!$C$30) -> 0 | F7: =IF(F$6=0,0,Inputs!$C$28*(1+Inputs!$C$29)^(F$6-1)*Inputs!$C$30) -> 0 | G7: =IF(G$6=0,0,Inputs!$C$28*(1+Inputs!$C$29)^(G$6-1)*Inputs!$C$30) -> 0 | H7: =IF(H$6=0,0,Inputs!$C$28*(1+Inputs!$C$29)^(H$6-1)*Inputs!$C$30) -> 0 | I7: =IF(I$6=0,0,Inputs!$C$28*(1+Inputs!$C$29)^(I$6-1)*Inputs!$C$30) -> 9 | J7: =IF(J$6=0,0,Inputs!$C$28*(1+Inputs!$C$29)^(J$6-1)*Inputs!$C$30) -> 10.8 | ... Z7: =IF(Z$6=0,0,Inputs!$C$28*(1+Inputs!$C$29)^(Z$6-1)*Inputs!$C$30) -> 199.675
B8: Subscribed agents | C8: =IF(C$6=0,0,Inputs!$C$31*(1+Inputs!$C$32)^(C$6-1)) -> 0 | D8: =IF(D$6=0,0,Inputs!$C$31*(1+Inputs!$C$32)^(D$6-1)) -> 0 | E8: =IF(E$6=0,0,Inputs!$C$31*(1+Inputs!$C$32)^(E$6-1)) -> 0 | F8: =IF(F$6=0,0,Inputs!$C$31*(1+Inputs!$C$32)^(F$6-1)) -> 0 | G8: =IF(G$6=0,0,Inputs!$C$31*(1+Inputs!$C$32)^(G$6-1)) -> 0 | H8: =IF(H$6=0,0,Inputs!$C$31*(1+Inputs!$C$32)^(H$6-1)) -> 0 | I8: =IF(I$6=0,0,Inputs!$C$31*(1+Inputs!$C$32)^(I$6-1)) -> 10 | J8: =IF(J$6=0,0,Inputs!$C$31*(1+Inputs!$C$32)^(J$6-1)) -> 11.5 | ... Z8: =IF(Z$6=0,0,Inputs!$C$31*(1+Inputs!$C$32)^(Z$6-1)) -> 107.61264
B9: Featured listings sold | C9: =IF(1<13,0,Inputs!$C$33) -> 0 | D9: =IF(2<13,0,Inputs!$C$33) -> 0 | E9: =IF(3<13,0,Inputs!$C$33) -> 0 | F9: =IF(4<13,0,Inputs!$C$33) -> 0 | G9: =IF(5<13,0,Inputs!$C$33) -> 0 | H9: =IF(6<13,0,Inputs!$C$33) -> 0 | I9: =IF(7<13,0,Inputs!$C$33) -> 0 | J9: =IF(8<13,0,Inputs!$C$33) -> 0 | K9: =IF(9<13,0,Inputs!$C$33) -> 0 | L9: =IF(10<13,0,Inputs!$C$33) -> 0 | M9: =IF(11<13,0,Inputs!$C$33) -> 0 | N9: =IF(12<13,0,Inputs!$C$33) -> 0 | O9: =IF(13<13,0,Inputs!$C$33) -> 0 | P9: =IF(14<13,0,Inputs!$C$33) -> 0 | Q9: =IF(15<13,0,Inputs!$C$33) -> 0 | R9: =IF(16<13,0,Inputs!$C$33) -> 0 | S9: =IF(17<13,0,Inputs!$C$33) -> 0 | T9: =IF(18<13,0,Inputs!$C$33) -> 0 | U9: =IF(19<13,0,Inputs!$C$33) -> 0 | V9: =IF(20<13,0,Inputs!$C$33) -> 0 | W9: =IF(21<13,0,Inputs!$C$33) -> 0 | X9: =IF(22<13,0,Inputs!$C$33) -> 0 | Y9: =IF(23<13,0,Inputs!$C$33) -> 0 | Z9: =IF(24<13,0,Inputs!$C$33) -> 0
B11: Revenue (GHS)
B12: Transaction fees | C12: =C7*'Unit economics'!$C$7 -> 0 | D12: =D7*'Unit economics'!$C$7 -> 0 | E12: =E7*'Unit economics'!$C$7 -> 0 | F12: =F7*'Unit economics'!$C$7 -> 0 | G12: =G7*'Unit economics'!$C$7 -> 0 | H12: =H7*'Unit economics'!$C$7 -> 0 | I12: =I7*'Unit economics'!$C$7 -> 4410 | J12: =J7*'Unit economics'!$C$7 -> 5292 | ... Z12: =Z7*'Unit economics'!$C$7 -> 97840.75
B13: Agent subscriptions | C13: =C8*Inputs!$C$7 -> 0 | D13: =D8*Inputs!$C$7 -> 0 | E13: =E8*Inputs!$C$7 -> 0 | F13: =F8*Inputs!$C$7 -> 0 | G13: =G8*Inputs!$C$7 -> 0 | H13: =H8*Inputs!$C$7 -> 0 | I13: =I8*Inputs!$C$7 -> 6000 | J13: =J8*Inputs!$C$7 -> 6900 | ... Z13: =Z8*Inputs!$C$7 -> 64567.584
B14: Featured listings | C14: =C9*Inputs!$C$8 -> 0 | D14: =D9*Inputs!$C$8 -> 0 | E14: =E9*Inputs!$C$8 -> 0 | F14: =F9*Inputs!$C$8 -> 0 | G14: =G9*Inputs!$C$8 -> 0 | H14: =H9*Inputs!$C$8 -> 0 | I14: =I9*Inputs!$C$8 -> 0 | J14: =J9*Inputs!$C$8 -> 0 | ... Z14: =Z9*Inputs!$C$8 -> 0
B15: Total revenue | C15: =SUM(C12:C14) -> 0 | D15: =SUM(D12:D14) -> 0 | E15: =SUM(E12:E14) -> 0 | F15: =SUM(F12:F14) -> 0 | G15: =SUM(G12:G14) -> 0 | H15: =SUM(H12:H14) -> 0 | I15: =SUM(I12:I14) -> 10410 | J15: =SUM(J12:J14) -> 12192 | ... Z15: =SUM(Z12:Z14) -> 162408.33
B17: Costs (GHS)
B18: Variable cost of transactions | C18: =C7*('Unit economics'!$C$13-'Unit economics'!$C$7) -> 0 | D18: =D7*('Unit economics'!$C$13-'Unit economics'!$C$7) -> 0 | E18: =E7*('Unit economics'!$C$13-'Unit economics'!$C$7) -> 0 | F18: =F7*('Unit economics'!$C$13-'Unit economics'!$C$7) -> 0 | G18: =G7*('Unit economics'!$C$13-'Unit economics'!$C$7) -> 0 | H18: =H7*('Unit economics'!$C$13-'Unit economics'!$C$7) -> 0 | I18: =I7*('Unit economics'!$C$13-'Unit economics'!$C$7) -> -2610 | J18: =J7*('Unit economics'!$C$13-'Unit economics'!$C$7) -> -3132 | ... Z18: =Z7*('Unit economics'!$C$13-'Unit economics'!$C$7) -> -57905.75
B19: Cost of serving agents | C19: =-C8*Inputs!$C$24 -> 0 | D19: =-D8*Inputs!$C$24 -> 0 | E19: =-E8*Inputs!$C$24 -> 0 | F19: =-F8*Inputs!$C$24 -> 0 | G19: =-G8*Inputs!$C$24 -> 0 | H19: =-H8*Inputs!$C$24 -> 0 | I19: =-I8*Inputs!$C$24 -> -400 | J19: =-J8*Inputs!$C$24 -> -460 | ... Z19: =-Z8*Inputs!$C$24 -> -4304.5056
B20: Fixed costs | C20: =-Inputs!$C$41 -> -85000 | D20: =-Inputs!$C$41 -> -85000 | E20: =-Inputs!$C$41 -> -85000 | F20: =-Inputs!$C$41 -> -85000 | G20: =-Inputs!$C$41 -> -85000 | H20: =-Inputs!$C$41 -> -85000 | I20: =-Inputs!$C$41 -> -85000 | J20: =-Inputs!$C$41 -> -85000 | ... Z20: =-Inputs!$C$41 -> -85000
B21: Total costs | C21: =SUM(C18:C20) -> -85000 | D21: =SUM(D18:D20) -> -85000 | E21: =SUM(E18:E20) -> -85000 | F21: =SUM(F18:F20) -> -85000 | G21: =SUM(G18:G20) -> -85000 | H21: =SUM(H18:H20) -> -85000 | I21: =SUM(I18:I20) -> -88010 | J21: =SUM(J18:J20) -> -88592 | ... Z21: =SUM(Z18:Z20) -> -147210.26
B23: Monthly profit / loss | C23: =C15+C21 -> -85000 | D23: =D15+D21 -> -85000 | E23: =E15+E21 -> -85000 | F23: =F15+F21 -> -85000 | G23: =G15+G21 -> -85000 | H23: =H15+H21 -> -85000 | I23: =I15+I21 -> -77600 | J23: =J15+J21 -> -76400 | ... Z23: =Z15+Z21 -> 15198.078
B24: Cash balance | C24: =Inputs!$C$44+C23 -> 315000 | D24: =C24+D23 -> 230000 | E24: =D24+E23 -> 145000 | F24: =E24+F23 -> 60000 | G24: =F24+G23 -> -25000 | H24: =G24+H23 -> -110000 | I24: =H24+I23 -> -187600 | J24: =I24+J23 -> -264000 | K24: =J24+K23 -> -339002 | ... Z24: =Y24+Z23 -> -984706.4
B26: Summary
B27: First profitable month | C27: =IFERROR("M"&MATCH(TRUE(),INDEX(C23:Z23>0,0),0),"not within 24 months") -> M23
B28: Cash at month 24 | C28: =Z24 -> -984706.4
B29: Lowest cash balance | C29: =MIN(C24:Z24) -> -1000586.3
B30: Revenue in month 24 | C30: =Z15 -> 162408.33
B31: Revenue in month 24 (USD) | C31: =IFERROR(Z15/Inputs!$C$45,0) -> 13534.028
B32: Total transactions over 24 months | C32: =SUM(C7:Z7) -> 1153.05
B34: Every figure here follows from the Inputs sheet. Replace the placeholders before showing this to anyone.
